{"0KhIT48muunN/0CtxTDCIg==":"clear_logo_url-500x237.png","rTmhLerHcfZyzrKXJc4M5g==":"img-9880-2000x1333.jpg","hDvifxEj9Rq7yTaT14W8mA==":"img-1855-2000x1333.jpg","Ivf5YHgfcQl00Lf4k8ytPQ==":"img-2811-2000x1333.jpg","gtwewFO9+gcBmAFJW/F5KA==":"img-9937-2000x1333.jpg","ti08ast+eALcQRyoIjsQQw==":"img-1855-5184x3456.jpg","MVRS1xTeVARv0oJp2OBSjg==":"img-9880-5184x3456.jpg","wXQhJFwC/R2tO2n0Vgpxdw==":"mbr-1623x1080.jpg","vWpFm1YxmGwCFdqW36WwCg==":"mbr-1620x1080.jpg","bMc6HJy0PFcQOTUZBj+WCg==":"img-43-5184x3456.jpg","AGxDDQaG7M5nNISBhfxDPg==":"img-9249-5184x3456.jpg","63+Kxhey8Tus84ERqxpkDA==":"mbr-1618x1080.jpg","xOzoWtKQgHNf1Q4QC3N/3w==":"mbr-1624x1080.jpg","8vRvodCfPs+oiGkFiilUag==":"mbr-1694x1080.jpg","tr0LnX5ZuQVTkILqWFcmoQ==":"241262889-381727107-1280x853.jpg","jFhKnvXP2ZVMj3Vee+SWiw==":"l-l_gxdcbqa-1280x853.jpg","Gj7oPvLr1QERx0HmEwiu2A==":"img-2825-5184x3456.jpg","wAC4byjJYSDGGPNMoEPmPg==":"6vcr5t4ow3o-1280x853.jpg","RA2dr/K3MW90erqoxBugWQ==":"mbr-1626x1080.jpg","fArdKACHtLA8oqVP3QK8Vg==":"img-9937-5184x3456.jpg","R0EmTZO/mSiL9fGJb0smog==":"img-2811-5184x3456.jpg","dMy4NKj93Lr7JEAUASA17Q==":"background4.jpg","syT2XmaLWCfkmkuQOxnyaQ==":"img-9912-5184x3456.jpg","NRgAgXh8LNIY50XCEA2EbA==":"qteyt9iknru-960x814.jpg","OkZx8/Hrj/h2LRrQCEztsg==":"pe6-qm7viv4-960x720.jpg","v7wLWFuJ+3UTzC+NvnwBAA==":"img-9749-2000x1333.jpg","jluFtk+pgt2rO6MtwuWYwA==":"img-9750-2000x1333.jpg","h3bW1r23jdk5kY1eKWvFjw==":"img-6126-4548x3456.jpg","D35/e8C40mr3IavCV79sgw==":"%D0%91%D0%B5%D0%B7%20%D0%B7%D0%B0%D0%B3%D0%BE%D0%BB%D0%BE%D0%B2%D0%BA%D0%B01-1009x719.png","j7qC0UqlPFYQJVXP/BVTzA==":"img-6126-2000x1519.jpg","cjzYMEw36/EDQQ5v+vOwmQ==":"img-9754-2000x1333.jpg","g8DGQO3a6ag3jTmgwu5lrQ==":"img-9754-5184x3456.jpg","sUbA98Bqa6Gfilbq/aLa/g==":"background1.jpg","/9ERXiMvMr1KGAEo/P6EiQ==":"background5.jpg","T4lc+nu/axWePrbcaafoZA==":"sad-2000x1333.jpg","FuHN7oF7ktD5MC2ETRzsPw==":"sad-1-2000x1333.jpg","NKN8SZo5/K/uvfhCH64Vrw==":"sad-2-2000x1333.jpg","f7aYuz5M5j58fHIt29IxjQ==":"logo_sad-1000x584.png","G7ppxFmBiA01WEKusq5Vzg==":"01.jpg","EHLXJz30A6msu4l2DcV76A==":"background2.jpg","Cfh6MwmAsMlOPp1R04FPbA==":"clear_logo_sad-500x237.png","7s+ZH0h9LUgYS20R4GqPGA==":"clear-logo-sad.png","Qiad1vptc02VBLLL9MzjLQ==":"sad1.jpg","YclKLhhbk4MyCxG4bDK9JQ==":"sad2.jpg","OCTQpjdsMSf9akcOwlWfCQ==":"sad3.jpg","uo3njR+YJgAduhSK2CSN1Q==":"sad4.jpg","K2MFrXbHpR+VKsj7H8DeOg==":"sad5.jpg","DXgf/rLIIs5Mqr6BWoOdag==":"sad6.jpg"}